spectrumchallenge/__init__.py
spectrumchallenge/client.py
SpectrumChallenge-0.0.1.dist-info/LICENSE
SpectrumChallenge-0.0.1.dist-info/METADATA
SpectrumChallenge-0.0.1.dist-info/WHEEL
SpectrumChallenge-0.0.1.dist-info/top_level.txt
SpectrumChallenge-0.0.1.dist-info/RECORD
