Metadata-Version: 2.1
Name: SpectrumChallenge
Version: 0.0.1
Summary: A code of Spectrum Challenge
Home-page: https://github.com/serp8291/spectrumchallenge
Author: serp82
Author-email: serp8291@gmail.com
License: MIT
Platform: UNKNOWN
Classifier: Programming Language :: Python :: 3
Classifier: License :: OSI Approved :: MIT License
Classifier: Operating System :: OS Independent
